COPYING.txt
LICENSE.txt
MANIFEST.in
PYTHON-LICENSE.txt
README.md
run-lit.py
setup.py
yalpt/__init__.py
yalpt/ansi_helper.py
yalpt/core.py
yalpt/formatters.py
yalpt/parsers.py
yalpt.egg-info/PKG-INFO
yalpt.egg-info/SOURCES.txt
yalpt.egg-info/dependency_links.txt
yalpt.egg-info/entry_points.txt
yalpt.egg-info/requires.txt
yalpt.egg-info/top_level.txt