Metadata-Version: 1.1
Name: yalpt
Version: 1.0.0
Summary: Yet Another Literate Python Tool
Home-page: https://github.com/directxman12/yalpt
Author: Solly Ross
Author-email: sross@redhat.com
License: ISC and PSF
Keywords: literate documentation tutorial
Platform: UNKNOWN
Classifier: Development Status :: 4 - Beta
Classifier: Intended Audience :: Developers
Classifier: Topic :: Documentation
Classifier: Topic :: Software Development
Classifier: License :: OSI Approved :: ISC License (ISCL)
Classifier: License :: OSI Approved :: Python Software Foundation License
Classifier: Programming Language :: Python :: 2
Classifier: Programming Language :: Python :: 2.7
Classifier: Programming Language :: Python :: 3
Classifier: Programming Language :: Python :: 3.3
Classifier: Programming Language :: Python :: 3.4
Classifier: Programming Language :: Python :: 3.5
